{
  "name": "Uptown Financial System - Redesigned",
  "image": "mcr.microsoft.com/devcontainers/javascript-node:20",
  "features": {
    "ghcr.io/devcontainers/features/git:1": {}
  },
  "forwardPorts": [3002, 5174, 8080],
  "portAttributes": {
    "3002": {
      "label": "Frontend Dev Server",
      "onAutoForward": "notify",
      "requireLocalPort": false
    },
    "5174": {
      "label": "Vite Dev Server",
      "onAutoForward": "notify",
      "requireLocalPort": false
    },
    "8080": {
      "label": "API Server",
      "onAutoForward": "notify",
      "requireLocalPort": false
    }
  },
  "postCreateCommand": "npm install",
  "customizations": {
    "vscode": {
      "extensions": [
        "dbaeumer.vscode-eslint",
        "esbenp.prettier-vscode",
        "bradlc.vscode-tailwindcss",
        "ms-vscode.vscode-typescript-next"
      ],
      "settings": {
        "editor.defaultFormatter": "esbenp.prettier-vscode",
        "editor.formatOnSave": true,
        "editor.codeActionsOnSave": {
          "source.fixAll.eslint": "explicit"
        }
      }
    }
  }
}
